<title>云计算部署实战</title>
<contents>
<ch01>OpenStack体验</ch01>
<p>云计算是一种模型，能够提供无论在何时何地都可以便捷获取所需资源的模型，这些资源可以是网络资源、存储资源、服务器资源、甚至是服务或者应用软件资源等，这些资源能够让用户根据需要快速创建应用，并且在不需要时进行资源释放。</p>
云计算是一种基于网络的计算模型，通过共享的计算资源，提供了按需获取、快速扩展和灵活使用计算资源的能力。在云计算中，存在三个主要的服务模型，分别是基础设施即服务（IaaS）、平台即服务（PaaS）和软件即服务（SaaS）：
https://developer.aliyun.com/article/1377320
<ch02>OpenStack搭建企业私有云</ch02>
<ch03>云存储</ch03>
<ch04>Fuel安装OpenStack</ch04>

<ch05>大数据Hadoop</ch05>
<ch06>Hbase数据库</ch06>
<ch07>部署CDH环境</ch07>
<ch08>云计算数据中心与亚马逊AWS</ch08>
</contents>